coroutx/__init__.py
coroutx/app.py
coroutx/async.py
coroutx/hub.py
coroutx/reqctx.py
coroutx/response.py
coroutx/route.py
coroutx-0.11.dev0.dist-info/DESCRIPTION.rst
coroutx-0.11.dev0.dist-info/METADATA
coroutx-0.11.dev0.dist-info/RECORD
coroutx-0.11.dev0.dist-info/WHEEL
coroutx-0.11.dev0.dist-info/metadata.json
coroutx-0.11.dev0.dist-info/top_level.txt
